ImagemBinaria/ImagemBinaria.py
ImagemBinaria/__init__.py
ImagemBinaria-0.0.7.dist-info/LICENSE.txt
ImagemBinaria-0.0.7.dist-info/METADATA
ImagemBinaria-0.0.7.dist-info/WHEEL
ImagemBinaria-0.0.7.dist-info/top_level.txt
ImagemBinaria-0.0.7.dist-info/RECORD
