Metadata-Version: 2.1
Name: ImagemBinaria
Version: 0.0.7
Summary: Operations with Binary Images.
Home-page: https://github.com/lucassl2020/POO2/tree/master/pacote
Author: Eurico Delmondes, Lucas Silva Lopes
Author-email: lucaslopes072009@hotmail.com
License: UNKNOWN
Platform: UNKNOWN
Classifier: Programming Language :: Python :: 3
Classifier: License :: OSI Approved :: MIT License
Classifier: Operating System :: OS Independent
Requires-Python: >=3.0
License-File: LICENSE.txt
Requires-Dist: opencv-python (>=4.5.3)
Requires-Dist: numpy (>=1.19.2)
